[
    {
      "title": "Modern Flat in Barcelona",
      "description": "A spacious and modern apartment located in the heart of Barcelona.",
      "rules": "No pets allowed. Quiet hours after 10 PM.",
      "rooms": 3,
      "beds": 4,
      "numBathrooms": 2,
      "maxPeople": 6,
      "pricePerNight": 120,
      "squareMeters": 90,
      "mainPhoto": "URL_to_main_photo",
      "services": {
        "airConditioning": true,
        "heating": true,
        "adaptedForReducedMobility": false,
        "television": true,
        "kitchen": true,
        "internet": true
      },
      "location": {
        "province": "Barcelona",
        "city": "Barcelona",
        "gpsCoordinates": [41.3851, 2.1734]
      },
      "additionalPhotos": [
        {
          "url": "URL_to_additional_photo_1",
          "caption": "Living room"
        },
        {
          "url": "URL_to_additional_photo_2",
          "caption": "Bedroom"
        },
        {
          "url": "URL_to_additional_photo_3",
          "caption": "Kitchen"
        }
      ],
      "isActive": true
    },
    {
      "title": "Cozy Beachside Apartment",
      "description": "Charming apartment near the beach in Sitges, perfect for a summer getaway.",
      "rules": "No smoking inside. No parties.",
      "rooms": 2,
      "beds": 3,
      "numBathrooms": 1,
      "maxPeople": 4,
      "pricePerNight": 100,
      "squareMeters": 70,
      "mainPhoto": "URL_to_main_photo",
      "services": {
        "airConditioning": true,
        "heating": false,
        "adaptedForReducedMobility": false,
        "television": true,
        "kitchen": true,
        "internet": true
      },
      "location": {
        "province": "Barcelona",
        "city": "Sitges",
        "gpsCoordinates": [41.2374, 1.8053]
      },
      "additionalPhotos": [
        {
          "url": "URL_to_additional_photo_1",
          "caption": "Beach view"
        },
        {
          "url": "URL_to_additional_photo_2",
          "caption": "Balcony"
        },
        {
          "url": "URL_to_additional_photo_3",
          "caption": "Bedroom"
        }
      ],
      "isActive": true
    },
    {
      "title": "Penthouse in Girona",
      "description": "A luxurious penthouse in the historical city of Girona, with stunning views.",
      "rules": "No pets. No loud music.",
      "rooms": 4,
      "beds": 5,
      "numBathrooms": 2,
      "maxPeople": 8,
      "pricePerNight": 150,
      "squareMeters": 120,
      "mainPhoto": "URL_to_main_photo",
      "services": {
        "airConditioning": true,
        "heating": true,
        "adaptedForReducedMobility": true,
        "television": true,
        "kitchen": true,
        "internet": true
      },
      "location": {
        "province": "Girona",
        "city": "Girona",
        "gpsCoordinates": [41.9831, 2.8249]
      },
      "additionalPhotos": [
        {
          "url": "URL_to_additional_photo_1",
          "caption": "Terrace view"
        },
        {
          "url": "URL_to_additional_photo_2",
          "caption": "Living room"
        },
        {
          "url": "URL_to_additional_photo_3",
          "caption": "Dining area"
        }
      ],
      "isActive": true
    },
    {
      "title": "Apartment near Sagrada Familia",
      "description": "Beautiful apartment just a 5-minute walk from the Sagrada Familia.",
      "rules": "No smoking. Respect the neighbors.",
      "rooms": 3,
      "beds": 4,
      "numBathrooms": 2,
      "maxPeople": 5,
      "pricePerNight": 110,
      "squareMeters": 85,
      "mainPhoto": "URL_to_main_photo",
      "services": {
        "airConditioning": true,
        "heating": true,
        "adaptedForReducedMobility": false,
        "television": true,
        "kitchen": true,
        "internet": true
      },
      "location": {
        "province": "Barcelona",
        "city": "Barcelona",
        "gpsCoordinates": [41.4036, 2.1744]
      },
      "additionalPhotos": [
        {
          "url": "URL_to_additional_photo_1",
          "caption": "Sagrada Familia view"
        },
        {
          "url": "URL_to_additional_photo_2",
          "caption": "Bedroom"
        },
        {
          "url": "URL_to_additional_photo_3",
          "caption": "Living area"
        }
      ],
      "isActive": true
    },
    {
      "title": "Rustic House in La Garrotxa",
      "description": "A peaceful rustic house surrounded by nature in the volcanic region of La Garrotxa.",
      "rules": "No loud parties. Respect nature.",
      "rooms": 4,
      "beds": 5,
      "numBathrooms": 2,
      "maxPeople": 7,
      "pricePerNight": 130,
      "squareMeters": 150,
      "mainPhoto": "URL_to_main_photo",
      "services": {
        "airConditioning": false,
        "heating": true,
        "adaptedForReducedMobility": false,
        "television": false,
        "kitchen": true,
        "internet": false
      },
      "location": {
        "province": "Girona",
        "city": "Olot",
        "gpsCoordinates": [42.1833, 2.4900]
      },
      "additionalPhotos": [
        {
          "url": "URL_to_additional_photo_1",
          "caption": "Garden"
        },
        {
          "url": "URL_to_additional_photo_2",
          "caption": "Bedroom"
        },
        {
          "url": "URL_to_additional_photo_3",
          "caption": "Dining area"
        }
      ],
      "isActive": true
    },
    {
        "title": "Luxury Loft in Girona",
        "description": "A luxury loft with stunning views of the city. Close to all amenities and attractions.",
        "rules": "No pets allowed. No smoking inside.",
        "rooms": 2,
        "beds": 3,
        "numBathrooms": 2,
        "maxPeople": 5,
        "pricePerNight": 150,
        "squareMeters": 110,
        "mainPhoto": "URL_to_main_photo",
        "services": {
            "airConditioning": true,
            "heating": true,
            "adaptedForReducedMobility": false,
            "television": true,
            "kitchen": true,
            "internet": true
        },
        "location": {
            "province": "Girona",
            "city": "Girona",
            "gpsCoordinates": [41.9794, 2.8214]
        },
        "additionalPhotos": [
        {
        "url": "URL_to_additional_photo_1",
        "caption": "City view from balcony"
        },
        {
        "url": "URL_to_additional_photo_2",
        "caption": "Modern kitchen"
        }
        ],
        "isActive": true
    },
    {
        "title": "Rustic House in Figueres",
        "description": "A charming rustic house in the town of Figueres, home of Salvador Dalí.",
        "rules": "No loud music after 11 PM. Pets allowed.",
        "rooms": 4,
        "beds": 6,
        "numBathrooms": 2,
        "maxPeople": 8,
        "pricePerNight": 200,
        "squareMeters": 150,
        "mainPhoto": "URL_to_main_photo",
        "services": {
            "airConditioning": false,
            "heating": true,
            "adaptedForReducedMobility": false,
            "television": true,
            "kitchen": true,
            "internet": false
        },
        "location": {
            "province": "Girona",
            "city": "Figueres",
            "gpsCoordinates": [42.2682, 2.9616]
        },
        "additionalPhotos": [
            {
            "url": "URL_to_additional_photo_1",
            "caption": "Rustic living room"
            },
            {
            "url": "URL_to_additional_photo_2",
            "caption": "Spacious garden"
            }
        ],
        "isActive": true
    },
    {
        "title": "Beachfront Apartment in Lloret de Mar",
        "description": "A bright apartment right on the beachfront in the popular Lloret de Mar.",
        "rules": "No smoking. No pets allowed.",
        "rooms": 3,
        "beds": 4,
        "numBathrooms": 2,
        "maxPeople": 6,
        "pricePerNight": 180,
        "squareMeters": 95,
        "mainPhoto": "URL_to_main_photo",
        "services": {
            "airConditioning": true,
            "heating": false,
            "adaptedForReducedMobility": true,
            "television": true,
            "kitchen": true,
            "internet": true
        },
        "location": {
            "province": "Girona",
            "city": "Lloret de Mar",
            "gpsCoordinates": [41.7002, 2.8456]
        },
        "additionalPhotos": [
            {
            "url": "URL_to_additional_photo_1",
            "caption": "Sea view from terrace"
            },
            {
            "url": "URL_to_additional_photo_2",
            "caption": "Modern living room"
            }
        ],
        "isActive": true
    },
    {
        "title": "Penthouse in Tarragona",
        "description": "A spacious penthouse with panoramic views of Tarragona and the Mediterranean.",
        "rules": "No parties allowed. Quiet hours after 10 PM.",
        "rooms": 3,
        "beds": 4,
        "numBathrooms": 2,
        "maxPeople": 5,
        "pricePerNight": 170,
        "squareMeters": 100,
        "mainPhoto": "URL_to_main_photo",
        "services": {
            "airConditioning": true,
            "heating": true,
            "adaptedForReducedMobility": false,
            "television": true,
            "kitchen": true,
            "internet": true
        },
        "location": {
            "province": "Tarragona",
            "city": "Tarragona",
            "gpsCoordinates": [41.1189, 1.2445]
        },
        "additionalPhotos": [
            {
            "url": "URL_to_additional_photo_1",
            "caption": "Penthouse terrace"
            },
            {
            "url": "URL_to_additional_photo_2",
            "caption": "Spacious dining area"
            }
        ],
        "isActive": true
    },
    {
        "title": "Modern Flat in Sabadell",
        "description": "A newly renovated modern flat in Sabadell, perfect for a family stay.",
        "rules": "No pets allowed. No smoking inside.",
        "rooms": 2,
        "beds": 3,
        "numBathrooms": 1,
        "maxPeople": 4,
        "pricePerNight": 90,
        "squareMeters": 85,
        "mainPhoto": "URL_to_main_photo",
        "services": {
            "airConditioning": true,
            "heating": true,
            "adaptedForReducedMobility": false,
            "television": true,
            "kitchen": true,
            "internet": true
        },
        "location": {
            "province": "Barcelona",
            "city": "Sabadell",
            "gpsCoordinates": [41.5489, 2.1076]
        },
        "additionalPhotos": [
            {
            "url": "URL_to_additional_photo_1",
            "caption": "Stylish living room"
            },
            {
            "url": "URL_to_additional_photo_2",
            "caption": "Bedroom with balcony"
            }
        ],
        "isActive": true
    },
    {
        "title": "Countryside Villa in Montseny",
        "description": "A tranquil countryside villa nestled in the Montseny mountains, perfect for nature lovers.",
        "rules": "Pets allowed. No loud music.",
        "rooms": 4,
        "beds": 5,
        "numBathrooms": 3,
        "maxPeople": 8,
        "pricePerNight": 220,
        "squareMeters": 180,
        "mainPhoto": "URL_to_main_photo",
        "services": {
            "airConditioning": false,
            "heating": true,
            "adaptedForReducedMobility": false,
            "television": true,
            "kitchen": true,
            "internet": false
        },
        "location": {
            "province": "Barcelona",
            "city": "Montseny",
            "gpsCoordinates": [41.7608, 2.3901]
        },
        "additionalPhotos": [
            {
            "url": "URL_to_additional_photo_1",
            "caption": "Mountain views"
            },
            {
            "url": "URL_to_additional_photo_2",
            "caption": "Spacious kitchen"
            }
        ],
        "isActive": true
    },
    {
        "title": "Apartment in Reus",
        "description": "A stylish apartment in the heart of Reus, near Gaudi's birthplace.",
        "rules": "No pets. Quiet hours after 11 PM.",
        "rooms": 2,
        "beds": 3,
        "numBathrooms": 1,
        "maxPeople": 4,
        "pricePerNight": 100,
        "squareMeters": 75,
        "mainPhoto": "URL_to_main_photo",
        "services": {
            "airConditioning": true,
            "heating": true,
            "adaptedForReducedMobility": true,
            "television": true,
            "kitchen": true,
            "internet": true
        },
        "location": {
            "province": "Tarragona",
            "city": "Reus",
            "gpsCoordinates": [41.1495, 1.1069]
        },
        "additionalPhotos": [
            {
            "url": "URL_to_additional_photo_1",
            "caption": "Living room with city view"
            },
            {
            "url": "URL_to_additional_photo_2",
            "caption": "Cozy bedroom"
            }
        ],
        "isActive": true
    },
    {
        "title": "Charming Flat in Badalona",
        "description": "A cozy and charming flat near the beach in Badalona, perfect for a weekend escape.",
        "rules": "No smoking. No pets.",
        "rooms": 2,
        "beds": 2,
        "numBathrooms": 1,
        "maxPeople": 4,
        "pricePerNight": 80,
        "squareMeters": 65,
        "mainPhoto": "URL_to_main_photo",
        "services": {
            "airConditioning": true,
            "heating": true,
            "adaptedForReducedMobility": false,
            "television": true,
            "kitchen": true,
            "internet": true
        },
        "location": {
            "province": "Barcelona",
            "city": "Badalona",
            "gpsCoordinates": [41.4500, 2.2474]
        },
        "additionalPhotos": [
            {
            "url": "URL_to_additional_photo_1",
            "caption": "Beach view from balcony"
            },
            {
            "url": "URL_to_additional_photo_2",
            "caption": "Bright living room"
            }
        ],
        "isActive": true
    },
    {
        "title": "Luxury Apartment in Sitges",
        "description": "A luxury apartment with private access to the beach in Sitges.",
        "rules": "No pets. No smoking.",
        "rooms": 3,
        "beds": 4,
        "numBathrooms": 2,
        "maxPeople": 5,
        "pricePerNight": 200,
        "squareMeters": 110,
        "mainPhoto": "URL_to_main_photo",
        "services": {
            "airConditioning": true,
            "heating": true,
            "adaptedForReducedMobility": true,
            "television": true,
            "kitchen": true,
            "internet": true
        },
        "location": {
            "province": "Barcelona",
            "city": "Sitges",
            "gpsCoordinates": [41.2374, 1.8053]
        },
        "additionalPhotos": [
            {
            "url": "URL_to_additional_photo_1",
            "caption": "Private beach access"
            },
            {
            "url": "URL_to_additional_photo_2",
            "caption": "Spacious dining room"
            }
        ],
        "isActive": true
    },
    {
        "title": "Historical House in Girona Old Town",
        "description": "A beautiful historical house located in the heart of Girona's Old Town.",
        "rules": "No loud noise after 10 PM. No pets.",
        "rooms": 4,
        "beds": 6,
        "numBathrooms": 3,
        "maxPeople": 8,
        "pricePerNight": 250,
        "squareMeters": 200,
        "mainPhoto": "URL_to_main_photo",
        "services": {
            "airConditioning": true,
            "heating": true,
            "adaptedForReducedMobility": false,
            "television": true,
            "kitchen": true,
            "internet": true
        },
        "location": {
            "province": "Girona",
            "city": "Girona",
            "gpsCoordinates": [41.9876, 2.8217]
        },
        "additionalPhotos": [
            {
            "url": "URL_to_additional_photo_1",
            "caption": "View of Girona Old Town"
            },
            {
            "url": "URL_to_additional_photo_2",
            "caption": "Spacious living room"
            }
        ],
        "isActive": true
    },
    {
        "title": "Seafront Villa in Cadaqués",
        "description": "A stunning seafront villa in Cadaqués with breathtaking views of the Mediterranean.",
        "rules": "No smoking. Pets allowed with prior approval.",
        "rooms": 5,
        "beds": 7,
        "numBathrooms": 4,
        "maxPeople": 10,
        "pricePerNight": 400,
        "squareMeters": 300,
        "mainPhoto": "URL_to_main_photo",
        "services": {
            "airConditioning": true,
            "heating": true,
            "adaptedForReducedMobility": true,
            "television": true,
            "kitchen": true,
            "internet": true
        },
        "location": {
            "province": "Girona",
            "city": "Cadaqués",
            "gpsCoordinates": [42.2889, 3.2783]
        },
        "additionalPhotos": [
            {
            "url": "URL_to_additional_photo_1",
            "caption": "Sea view from terrace"
            },
            {
            "url": "URL_to_additional_photo_2",
            "caption": "Private pool"
            }
        ],
        "isActive": true
    },
    {
        "title": "Modern Flat in Manresa",
        "description": "A contemporary flat in the heart of Manresa, ideal for business trips or short stays.",
        "rules": "No smoking. No parties.",
        "rooms": 2,
        "beds": 3,
        "numBathrooms": 1,
        "maxPeople": 4,
        "pricePerNight": 75,
        "squareMeters": 80,
        "mainPhoto": "URL_to_main_photo",
        "services": {
            "airConditioning": true,
            "heating": true,
            "adaptedForReducedMobility": false,
            "television": true,
            "kitchen": true,
            "internet": true
        },
        "location": {
            "province": "Barcelona",
            "city": "Manresa",
            "gpsCoordinates": [41.7275, 1.8269]
        },
        "additionalPhotos": [
            {
            "url": "URL_to_additional_photo_1",
            "caption": "Modern living room"
            },
            {
            "url": "URL_to_additional_photo_2",
            "caption": "Stylish kitchen"
            }
        ],
        "isActive": true
    },
    {
        "title": "Apartment in Vilanova i la Geltrú",
        "description": "A family-friendly apartment near the beach in Vilanova i la Geltrú.",
        "rules": "No pets allowed. No parties.",
        "rooms": 3,
        "beds": 4,
        "numBathrooms": 2,
        "maxPeople": 6,
        "pricePerNight": 140,
        "squareMeters": 100,
        "mainPhoto": "URL_to_main_photo",
        "services": {
            "airConditioning": true,
            "heating": true,
            "adaptedForReducedMobility": true,
            "television": true,
            "kitchen": true,
            "internet": true
        },
        "location": {
            "province": "Barcelona",
            "city": "Vilanova i la Geltrú",
            "gpsCoordinates": [41.2240, 1.7255]
        },
        "additionalPhotos": [
            {
            "url": "URL_to_additional_photo_1",
            "caption": "Beachfront view"
            },
            {
            "url": "URL_to_additional_photo_2",
            "caption": "Spacious living room"
            }
        ],
        "isActive": true
    },
    {
        "title": "Townhouse in Vic",
        "description": "A charming townhouse in the historical town of Vic.",
        "rules": "No loud noise after 11 PM. No pets.",
        "rooms": 3,
        "beds": 4,
        "numBathrooms": 2,
        "maxPeople": 5,
        "pricePerNight": 130,
        "squareMeters": 95,
        "mainPhoto": "URL_to_main_photo",
        "services": {
            "airConditioning": true,
            "heating": true,
            "adaptedForReducedMobility": false,
            "television": true,
            "kitchen": true,
            "internet": true
        },
        "location": {
            "province": "Barcelona",
            "city": "Vic",
            "gpsCoordinates": [41.9302, 2.2549]
        },
        "additionalPhotos": [
            {
            "url": "URL_to_additional_photo_1",
            "caption": "Historical architecture"
            },
            {
            "url": "URL_to_additional_photo_2",
            "caption": "Living room with fireplace"
            }
        ],
        "isActive": true
    },
    {
        "title": "Studio Apartment in Blanes",
        "description": "A compact studio apartment perfect for solo travelers or couples, located in Blanes.",
        "rules": "No pets allowed. No smoking.",
        "rooms": 1,
        "beds": 1,
        "numBathrooms": 1,
        "maxPeople": 2,
        "pricePerNight": 60,
        "squareMeters": 45,
        "mainPhoto": "URL_to_main_photo",
        "services": {
            "airConditioning": true,
            "heating": true,
            "adaptedForReducedMobility": true,
            "television": true,
            "kitchen": true,
            "internet": true
        },
        "location": {
            "province": "Girona",
            "city": "Blanes",
            "gpsCoordinates": [41.6740, 2.7905]
        },
        "additionalPhotos": [
            {
            "url": "URL_to_additional_photo_1",
            "caption": "Cozy interior"
            },
            {
            "url": "URL_to_additional_photo_2",
            "caption": "Beach view"
            }
        ],
        "isActive": true
    },
    {
        "title": "Cottage in Camprodon",
        "description": "A rustic cottage in the picturesque town of Camprodon, surrounded by nature.",
        "rules": "Pets allowed. No loud music after 10 PM.",
        "rooms": 3,
        "beds": 4,
        "numBathrooms": 2,
        "maxPeople": 6,
        "pricePerNight": 160,
        "squareMeters": 120,
        "mainPhoto": "URL_to_main_photo",
        "services": {
            "airConditioning": false,
            "heating": true,
            "adaptedForReducedMobility": false,
            "television": true,
            "kitchen": true,
            "internet": false
        },
        "location": {
            "province": "Girona",
            "city": "Camprodon",
            "gpsCoordinates": [42.3158, 2.3721]
        },
        "additionalPhotos": [
            {
            "url": "URL_to_additional_photo_1",
            "caption": "Beautiful garden"
            },
            {
            "url": "URL_to_additional_photo_2",
            "caption": "Rustic living room"
            }
        ],
        "isActive": true
    }
]
  